printmate/__init__.py
printmate/printmate.py
printmate-1.4.8.dist-info/METADATA
printmate-1.4.8.dist-info/WHEEL
printmate-1.4.8.dist-info/license
printmate-1.4.8.dist-info/top_level.txt
printmate-1.4.8.dist-info/RECORD
