Metadata-Version: 2.2
Name: printmate
Version: 1.4.8
Summary: A library used to print animated and colored text
Author-email: Universal CEO <universal.store.panel@gmail.com>
License: This software is provided by PyGaps under the following terms:
Classifier: Programming Language :: Python :: 3
Classifier: License :: OSI Approved :: MIT License
Classifier: Operating System :: OS Independent
Requires-Python: >=3.6
License-File: license
